docs/__init__.py
pytestFlexReport/__init__.py
pytestFlexReport/module_define_init_.py
pytestFlexReport/plugin.py
pytestFlexReport/pytest_flexreport.py
pytestFlexReport/utils.py
pytestFlexReport/templates/__init__.py
pytestFlexReport/templates/template1.html
pytestFlexReport/templates/template2.html
pytestFlexReport/templates/template3.html
pytestFlexReport/templates/static/__init__.py
pytestFlexReport/templates/static/bootstrap.min.css
pytestFlexReport/templates/static/echarts.min.js
pytestFlexReport/templates/static/jquery.slim.min.js
tests/__init__.py
tests/conftest.py
tests/run.py
tests/test_demo1.py
tests/test_demo2.py
tests/test_demo3.py
pytest_flexreport-1.2.6.dist-info/LICENSE
pytest_flexreport-1.2.6.dist-info/METADATA
pytest_flexreport-1.2.6.dist-info/WHEEL
pytest_flexreport-1.2.6.dist-info/entry_points.txt
pytest_flexreport-1.2.6.dist-info/top_level.txt
pytest_flexreport-1.2.6.dist-info/RECORD
